dart_sass/__init__.py
dart_sass/canonicalize_context.py
dart_sass/cli.py
dart_sass/compile.py
dart_sass/compiler_path.py
dart_sass/deprecations.py
dart_sass/deprotofy_span.py
dart_sass/dispatcher.py
dart_sass/exception.py
dart_sass/function_registry.py
dart_sass/importer_registry.py
dart_sass/logger.py
dart_sass/message_transformer.py
dart_sass/packet_transformer.py
dart_sass/request_tracker.py
dart_sass/types.py
dart_sass/utils.py
dart_sass/value_converter.py
dart_sass/varint_decoder.py
dart_sass/version.py
dart_sass/compiler/__init__.py
dart_sass/compiler/async_compiler.py
dart_sass/compiler/sync_compiler.py
dart_sass/compiler/utils.py
dart_sass/value/__init__.py
dart_sass/value/argument_list.py
dart_sass/value/base.py
dart_sass/value/boolean.py
dart_sass/value/calculations.py
dart_sass/value/color.py
dart_sass/value/function.py
dart_sass/value/list.py
dart_sass/value/map.py
dart_sass/value/mixin.py
dart_sass/value/null.py
dart_sass/value/number.py
dart_sass/value/string.py
dart_sass/vendor/__init__.py
dart_sass/vendor/embedded_sass.proto
dart_sass/vendor/embedded_sass_pb2.py
dart_sass/vendor/embedded_sass_pb2.pyi
python_dart_sass-0.1.0.dist-info/METADATA
python_dart_sass-0.1.0.dist-info/WHEEL
python_dart_sass-0.1.0.dist-info/entry_points.txt
python_dart_sass-0.1.0.dist-info/RECORD
