Metadata-Version: 2.4
Name: python-dart-sass
Version: 0.1.0
Summary: Python implementation of the Embedded Sass Host using the Dart Sass embedded protocol
Project-URL: Homepage, https://github.com/hmcqueen/python-dart-sass
Project-URL: Repository, https://github.com/hmcqueen/python-dart-sass
Project-URL: Documentation, https://github.com/hmcqueen/python-dart-sass#readme
Project-URL: Bug Tracker, https://github.com/hmcqueen/python-dart-sass/issues
Project-URL: Changelog, https://github.com/hmcqueen/python-dart-sass/blob/main/CHANGELOG.md
Author-email: Harvey McQueen <hmcqueen@gmail.com>
Maintainer-email: Harvey McQueen <hmcqueen@gmail.com>
License-Expression: MIT
Keywords: compiler,css,dart-sass,embedded,sass,scss,stylesheet
Classifier: Development Status :: 3 - Alpha
Classifier: Intended Audience :: Developers
Classifier: License :: OSI Approved :: MIT License
Classifier: Programming Language :: Python :: 3
Classifier: Programming Language :: Python :: 3.10
Classifier: Programming Language :: Python :: 3.11
Classifier: Programming Language :: Python :: 3.12
Classifier: Topic :: Internet :: WWW/HTTP :: Dynamic Content
Classifier: Topic :: Software Development :: Libraries :: Python Modules
Classifier: Topic :: Software Development :: Pre-processors
Classifier: Topic :: Text Processing :: Markup
Requires-Python: >=3.10
Requires-Dist: colorspacious>=1.1.0
Requires-Dist: immutables>=0.15
Requires-Dist: protobuf>=4.21.0
Requires-Dist: reactivex>=4.0.0
Requires-Dist: varint>=1.0.2
Provides-Extra: dev
Requires-Dist: black>=23.0.0; extra == 'dev'
Requires-Dist: grpcio-tools>=1.70.0; extra == 'dev'
Requires-Dist: isort>=5.12.0; extra == 'dev'
Requires-Dist: mypy-protobuf>=3.6.0; extra == 'dev'
Requires-Dist: mypy>=1.0.0; extra == 'dev'
Requires-Dist: pytest-asyncio>=0.21.0; extra == 'dev'
Requires-Dist: pytest-cov>=4.0.0; extra == 'dev'
Requires-Dist: pytest>=7.0.0; extra == 'dev'
Requires-Dist: ruff>=0.1.0; extra == 'dev'
